{
    "experiment_name": "overfit",
    "seed": 42,
    "data_path": "dataset/Pride_and_Prejudice-Jane_Austen.txt",
    "tokenization_level": "word",
    "vocab_size": 10000,
    "min_freq": 2,
    "train_ratio": 0.8,
    "val_ratio": 0.1,
    "seq_length": 35,
    "batch_size": 32,
    "embedding_dim": 512,
    "hidden_dim": 512,
    "num_layers": 3,
    "dropout": 0.0,
    "tie_weights": false,
    "learning_rate": 0.002,
    "num_epochs": 100,
    "clip_grad": 5.0,
    "early_stopping_patience": 100,
    "output_dir": "outputs",
    "checkpoint_dir": "checkpoints",
    "plots_dir": "plots"
}
